multi_menu/__init__.py
multi_menu/frontend/build/asset-manifest.json
multi_menu/frontend/build/bootstrap.min.css
multi_menu/frontend/build/index.html
multi_menu/frontend/build/static/js/main.be017e89.js
multi_menu/frontend/build/static/js/main.be017e89.js.LICENSE.txt
multi_menu/frontend/build/static/js/main.be017e89.js.map
streamlit_multi_menu/__init__.py
streamlit_multi_menu/frontend/build/asset-manifest.json
streamlit_multi_menu/frontend/build/bootstrap.min.css
streamlit_multi_menu/frontend/build/index.html
streamlit_multi_menu/frontend/build/static/js/main.be017e89.js
streamlit_multi_menu/frontend/build/static/js/main.be017e89.js.LICENSE.txt
streamlit_multi_menu/frontend/build/static/js/main.be017e89.js.map
streamlit_multi_menu-0.1.0.dist-info/LICENSE
streamlit_multi_menu-0.1.0.dist-info/METADATA
streamlit_multi_menu-0.1.0.dist-info/WHEEL
streamlit_multi_menu-0.1.0.dist-info/top_level.txt
streamlit_multi_menu-0.1.0.dist-info/RECORD
