Metadata-Version: 2.1
Name: streamlit_multi_menu
Version: 0.1.0
Summary: Streamlit component that allows you to render a menu widget with multiple columns but with only one globally selected value. It is possible to use photos for background inside the menu buttons.
Home-page: 
Author: Mikkel Lorenz
Author-email: mvlorenz@protonmail.com
Requires-Python: >=3.7
License-File: LICENSE
Provides-Extra: devel
Requires-Dist: wheel ; extra == 'devel'
Requires-Dist: pytest ==7.4.0 ; extra == 'devel'
Requires-Dist: playwright ==1.39.0 ; extra == 'devel'
Requires-Dist: requests ==2.31.0 ; extra == 'devel'
Requires-Dist: pytest-playwright-snapshot ==1.0 ; extra == 'devel'
Requires-Dist: pytest-rerunfailures ==12.0 ; extra == 'devel'
